cert_alert/__init__.py
cert_alert/__main__.py
cert_alert/cert_alert.py
cert_alert/config_loader.py
cert_alert/models.py
cert_alert-0.0.1.dist-info/METADATA
cert_alert-0.0.1.dist-info/WHEEL
cert_alert-0.0.1.dist-info/entry_points.txt
cert_alert-0.0.1.dist-info/top_level.txt
cert_alert-0.0.1.dist-info/RECORD
