Metadata-Version: 2.4
Name: cert-alert
Version: 0.0.1
Summary: CLI to test TLS certificate expiry
Author-email: xoryouyou <xoryouyou@gmail.com>
License-Expression: MIT
Project-URL: Homepage, https://github.com/xoryouyou/cert-alert
Project-URL: Issues, https://github.com/xoryouyou/cert-alert/issues
Requires-Python: >=3.11
Requires-Dist: argparse>=1.4.0
Requires-Dist: coloredlogs>=15.0.1
Requires-Dist: cryptography>=44.0.0
Requires-Dist: pydantic>=2.10.6
Requires-Dist: pytest>=8.3.4
Requires-Dist: pyyaml>=6.0.2
